{"id":"gQqz","dependencies":[{"name":"C:\\Users\\user\\Desktop\\铁塔\\tower\\node_modules\\echarts\\package.json","includedInParent":true,"mtime":1577984109921},{"name":"C:\\Users\\user\\Desktop\\铁塔\\tower\\package.json","includedInParent":true,"mtime":1577981361515},{"name":"C:\\Users\\user\\Desktop\\铁塔\\tower\\.babelrc","includedInParent":true,"mtime":1577778028910}],"generated":{"js":"function e(e){var t={};e.eachSeriesByType(\"graph\",function(e){var o=e.getCategoriesData(),a=e.getData(),l={};o.each(function(a){var r=o.getName(a);l[\"ec-\"+r]=a;var c=o.getItemModel(a).get(\"itemStyle.color\")||e.getColorFromPalette(r,t);o.setItemVisual(a,\"color\",c)}),o.count()&&a.each(function(e){var t=a.getItemModel(e).getShallow(\"category\");null!=t&&(\"string\"==typeof t&&(t=l[\"ec-\"+t]),a.getItemVisual(e,\"color\",!0)||a.setItemVisual(e,\"color\",o.getItemVisual(t,\"color\")))})})}module.exports=e;","map":{"mappings":[{"source":"..\\node_modules\\echarts\\lib\\chart\\graph\\categoryVisual.js","original":{"line":39,"column":0},"generated":{"line":1,"column":0}},{"source":"..\\node_modules\\echarts\\lib\\chart\\graph\\categoryVisual.js","original":{"line":39,"column":0},"generated":{"line":1,"column":9}},{"source":"..\\node_modules\\echarts\\lib\\chart\\graph\\categoryVisual.js","original":{"line":39,"column":0},"generated":{"line":1,"column":11}},{"source":"..\\node_modules\\echarts\\lib\\chart\\graph\\categoryVisual.js","original":{"line":40,"column":0},"generated":{"line":1,"column":14}},{"source":"..\\node_modules\\echarts\\lib\\chart\\graph\\categoryVisual.js","original":{"line":40,"column":0},"generated":{"line":1,"column":18}},{"source":"..\\node_modules\\echarts\\lib\\chart\\graph\\categoryVisual.js","original":{"line":40,"column":0},"generated":{"line":1,"column":20}},{"source":"..\\node_modules\\echarts\\lib\\chart\\graph\\categoryVisual.js","original":{"line":41,"column":0},"generated":{"line":1,"column":23}},{"source":"..\\node_modules\\echarts\\lib\\chart\\graph\\categoryVisual.js","original":{"line":41,"column":0},"generated":{"line":1,"column":25}},{"source":"..\\node_modules\\echarts\\lib\\chart\\graph\\categoryVisual.js","original":{"line":41,"column":0},"generated":{"line":1,"column":42}},{"source":"..\\node_modules\\echarts\\lib\\chart\\graph\\categoryVisual.js","original":{"line":41,"column":0},"generated":{"line":1,"column":50}},{"source":"..\\node_modules\\echarts\\lib\\chart\\graph\\categoryVisual.js","original":{"line":41,"column":0},"generated":{"line":1,"column":59}},{"source":"..\\node_modules\\echarts\\lib\\chart\\graph\\categoryVisual.js","original":{"line":42,"column":0},"generated":{"line":1,"column":62}},{"source":"..\\node_modules\\echarts\\lib\\chart\\graph\\categoryVisual.js","original":{"line":42,"column":0},"generated":{"line":1,"column":66}},{"source":"..\\node_modules\\echarts\\lib\\chart\\graph\\categoryVisual.js","original":{"line":42,"column":0},"generated":{"line":1,"column":68}},{"source":"..\\node_modules\\echarts\\lib\\chart\\graph\\categoryVisual.js","original":{"line":42,"column":0},"generated":{"line":1,"column":70}},{"source":"..\\node_modules\\echarts\\lib\\chart\\graph\\categoryVisual.js","original":{"line":43,"column":0},"generated":{"line":1,"column":90}},{"source":"..\\node_modules\\echarts\\lib\\chart\\graph\\categoryVisual.js","original":{"line":43,"column":0},"generated":{"line":1,"column":92}},{"source":"..\\node_modules\\echarts\\lib\\chart\\graph\\categoryVisual.js","original":{"line":43,"column":0},"generated":{"line":1,"column":94}},{"source":"..\\node_modules\\echarts\\lib\\chart\\graph\\categoryVisual.js","original":{"line":44,"column":0},"generated":{"line":1,"column":104}},{"source":"..\\node_modules\\echarts\\lib\\chart\\graph\\categoryVisual.js","original":{"line":44,"column":0},"generated":{"line":1,"column":106}},{"source":"..\\node_modules\\echarts\\lib\\chart\\graph\\categoryVisual.js","original":{"line":45,"column":0},"generated":{"line":1,"column":109}},{"source":"..\\node_modules\\echarts\\lib\\chart\\graph\\categoryVisual.js","original":{"line":45,"column":0},"generated":{"line":1,"column":111}},{"source":"..\\node_modules\\echarts\\lib\\chart\\graph\\categoryVisual.js","original":{"line":45,"column":0},"generated":{"line":1,"column":116}},{"source":"..\\node_modules\\echarts\\lib\\chart\\graph\\categoryVisual.js","original":{"line":45,"column":0},"generated":{"line":1,"column":125}},{"source":"..\\node_modules\\echarts\\lib\\chart\\graph\\categoryVisual.js","original":{"line":46,"column":0},"generated":{"line":1,"column":128}},{"source":"..\\node_modules\\echarts\\lib\\chart\\graph\\categoryVisual.js","original":{"line":46,"column":0},"generated":{"line":1,"column":132}},{"source":"..\\node_modules\\echarts\\lib\\chart\\graph\\categoryVisual.js","original":{"line":46,"column":0},"generated":{"line":1,"column":134}},{"source":"..\\node_modules\\echarts\\lib\\chart\\graph\\categoryVisual.js","original":{"line":46,"column":0},"generated":{"line":1,"column":136}},{"source":"..\\node_modules\\echarts\\lib\\chart\\graph\\categoryVisual.js","original":{"line":46,"column":0},"generated":{"line":1,"column":144}},{"source":"..\\node_modules\\echarts\\lib\\chart\\graph\\categoryVisual.js","original":{"line":48,"column":0},"generated":{"line":1,"column":147}},{"source":"..\\node_modules\\echarts\\lib\\chart\\graph\\categoryVisual.js","original":{"line":48,"column":0},"generated":{"line":1,"column":149}},{"source":"..\\node_modules\\echarts\\lib\\chart\\graph\\categoryVisual.js","original":{"line":48,"column":0},"generated":{"line":1,"column":155}},{"source":"..\\node_modules\\echarts\\lib\\chart\\graph\\categoryVisual.js","original":{"line":48,"column":0},"generated":{"line":1,"column":158}},{"source":"..\\node_modules\\echarts\\lib\\chart\\graph\\categoryVisual.js","original":{"line":49,"column":0},"generated":{"line":1,"column":160}},{"source":"..\\node_modules\\echarts\\lib\\chart\\graph\\categoryVisual.js","original":{"line":50,"column":0},"generated":{"line":1,"column":164}},{"source":"..\\node_modules\\echarts\\lib\\chart\\graph\\categoryVisual.js","original":{"line":49,"column":0},"generated":{"line":1,"column":166}},{"source":"..\\node_modules\\echarts\\lib\\chart\\graph\\categoryVisual.js","original":{"line":49,"column":0},"generated":{"line":1,"column":168}},{"source":"..\\node_modules\\echarts\\lib\\chart\\graph\\categoryVisual.js","original":{"line":49,"column":0},"generated":{"line":1,"column":181}},{"source":"..\\node_modules\\echarts\\lib\\chart\\graph\\categoryVisual.js","original":{"line":50,"column":0},"generated":{"line":1,"column":184}},{"source":"..\\node_modules\\echarts\\lib\\chart\\graph\\categoryVisual.js","original":{"line":50,"column":0},"generated":{"line":1,"column":188}},{"source":"..\\node_modules\\echarts\\lib\\chart\\graph\\categoryVisual.js","original":{"line":50,"column":0},"generated":{"line":1,"column":208}},{"source":"..\\node_modules\\echarts\\lib\\chart\\graph\\categoryVisual.js","original":{"line":50,"column":0},"generated":{"line":1,"column":210}},{"source":"..\\node_modules\\echarts\\lib\\chart\\graph\\categoryVisual.js","original":{"line":50,"column":0},"generated":{"line":1,"column":230}},{"source":"..\\node_modules\\echarts\\lib\\chart\\graph\\categoryVisual.js","original":{"line":50,"column":0},"generated":{"line":1,"column":232}},{"source":"..\\node_modules\\echarts\\lib\\chart\\graph\\categoryVisual.js","original":{"line":51,"column":0},"generated":{"line":1,"column":235}},{"source":"..\\node_modules\\echarts\\lib\\chart\\graph\\categoryVisual.js","original":{"line":51,"column":0},"generated":{"line":1,"column":237}},{"source":"..\\node_modules\\echarts\\lib\\chart\\graph\\categoryVisual.js","original":{"line":51,"column":0},"generated":{"line":1,"column":251}},{"source":"..\\node_modules\\echarts\\lib\\chart\\graph\\categoryVisual.js","original":{"line":51,"column":0},"generated":{"line":1,"column":253}},{"source":"..\\node_modules\\echarts\\lib\\chart\\graph\\categoryVisual.js","original":{"line":51,"column":0},"generated":{"line":1,"column":261}},{"source":"..\\node_modules\\echarts\\lib\\chart\\graph\\categoryVisual.js","original":{"line":54,"column":0},"generated":{"line":1,"column":266}},{"source":"..\\node_modules\\echarts\\lib\\chart\\graph\\categoryVisual.js","original":{"line":54,"column":0},"generated":{"line":1,"column":268}},{"source":"..\\node_modules\\echarts\\lib\\chart\\graph\\categoryVisual.js","original":{"line":55,"column":0},"generated":{"line":1,"column":277}},{"source":"..\\node_modules\\echarts\\lib\\chart\\graph\\categoryVisual.js","original":{"line":55,"column":0},"generated":{"line":1,"column":279}},{"source":"..\\node_modules\\echarts\\lib\\chart\\graph\\categoryVisual.js","original":{"line":55,"column":0},"generated":{"line":1,"column":284}},{"source":"..\\node_modules\\echarts\\lib\\chart\\graph\\categoryVisual.js","original":{"line":55,"column":0},"generated":{"line":1,"column":293}},{"source":"..\\node_modules\\echarts\\lib\\chart\\graph\\categoryVisual.js","original":{"line":56,"column":0},"generated":{"line":1,"column":296}},{"source":"..\\node_modules\\echarts\\lib\\chart\\graph\\categoryVisual.js","original":{"line":57,"column":0},"generated":{"line":1,"column":300}},{"source":"..\\node_modules\\echarts\\lib\\chart\\graph\\categoryVisual.js","original":{"line":56,"column":0},"generated":{"line":1,"column":302}},{"source":"..\\node_modules\\echarts\\lib\\chart\\graph\\categoryVisual.js","original":{"line":56,"column":0},"generated":{"line":1,"column":304}},{"source":"..\\node_modules\\echarts\\lib\\chart\\graph\\categoryVisual.js","original":{"line":56,"column":0},"generated":{"line":1,"column":317}},{"source":"..\\node_modules\\echarts\\lib\\chart\\graph\\categoryVisual.js","original":{"line":57,"column":0},"generated":{"line":1,"column":320}},{"source":"..\\node_modules\\echarts\\lib\\chart\\graph\\categoryVisual.js","original":{"line":57,"column":0},"generated":{"line":1,"column":331}},{"source":"..\\node_modules\\echarts\\lib\\chart\\graph\\categoryVisual.js","original":{"line":59,"column":0},"generated":{"line":1,"column":343}},{"source":"..\\node_modules\\echarts\\lib\\chart\\graph\\categoryVisual.js","original":{"line":59,"column":0},"generated":{"line":1,"column":349}},{"source":"..\\node_modules\\echarts\\lib\\chart\\graph\\categoryVisual.js","original":{"line":60,"column":0},"generated":{"line":1,"column":353}},{"source":"..\\node_modules\\echarts\\lib\\chart\\graph\\categoryVisual.js","original":{"line":60,"column":0},"generated":{"line":1,"column":370}},{"source":"..\\node_modules\\echarts\\lib\\chart\\graph\\categoryVisual.js","original":{"line":61,"column":0},"generated":{"line":1,"column":374}},{"source":"..\\node_modules\\echarts\\lib\\chart\\graph\\categoryVisual.js","original":{"line":61,"column":0},"generated":{"line":1,"column":376}},{"source":"..\\node_modules\\echarts\\lib\\chart\\graph\\categoryVisual.js","original":{"line":61,"column":0},"generated":{"line":1,"column":378}},{"source":"..\\node_modules\\echarts\\lib\\chart\\graph\\categoryVisual.js","original":{"line":61,"column":0},"generated":{"line":1,"column":384}},{"source":"..\\node_modules\\echarts\\lib\\chart\\graph\\categoryVisual.js","original":{"line":64,"column":0},"generated":{"line":1,"column":388}},{"source":"..\\node_modules\\echarts\\lib\\chart\\graph\\categoryVisual.js","original":{"line":64,"column":0},"generated":{"line":1,"column":390}},{"source":"..\\node_modules\\echarts\\lib\\chart\\graph\\categoryVisual.js","original":{"line":64,"column":0},"generated":{"line":1,"column":404}},{"source":"..\\node_modules\\echarts\\lib\\chart\\graph\\categoryVisual.js","original":{"line":64,"column":0},"generated":{"line":1,"column":406}},{"source":"..\\node_modules\\echarts\\lib\\chart\\graph\\categoryVisual.js","original":{"line":64,"column":0},"generated":{"line":1,"column":415}},{"source":"..\\node_modules\\echarts\\lib\\chart\\graph\\categoryVisual.js","original":{"line":65,"column":0},"generated":{"line":1,"column":419}},{"source":"..\\node_modules\\echarts\\lib\\chart\\graph\\categoryVisual.js","original":{"line":65,"column":0},"generated":{"line":1,"column":421}},{"source":"..\\node_modules\\echarts\\lib\\chart\\graph\\categoryVisual.js","original":{"line":65,"column":0},"generated":{"line":1,"column":435}},{"source":"..\\node_modules\\echarts\\lib\\chart\\graph\\categoryVisual.js","original":{"line":65,"column":0},"generated":{"line":1,"column":437}},{"source":"..\\node_modules\\echarts\\lib\\chart\\graph\\categoryVisual.js","original":{"line":65,"column":0},"generated":{"line":1,"column":445}},{"source":"..\\node_modules\\echarts\\lib\\chart\\graph\\categoryVisual.js","original":{"line":65,"column":0},"generated":{"line":1,"column":447}},{"source":"..\\node_modules\\echarts\\lib\\chart\\graph\\categoryVisual.js","original":{"line":65,"column":0},"generated":{"line":1,"column":461}},{"source":"..\\node_modules\\echarts\\lib\\chart\\graph\\categoryVisual.js","original":{"line":65,"column":0},"generated":{"line":1,"column":463}},{"source":"..\\node_modules\\echarts\\lib\\chart\\graph\\categoryVisual.js","original":{"line":73,"column":0},"generated":{"line":1,"column":478}},{"source":"..\\node_modules\\echarts\\lib\\chart\\graph\\categoryVisual.js","original":{"line":73,"column":0},"generated":{"line":1,"column":485}},{"source":"..\\node_modules\\echarts\\lib\\chart\\graph\\categoryVisual.js","original":{"line":73,"column":0},"generated":{"line":1,"column":493}}],"sources":{"..\\node_modules\\echarts\\lib\\chart\\graph\\categoryVisual.js":"\n/*\n* Licensed to the Apache Software Foundation (ASF) under one\n* or more contributor license agreements.  See the NOTICE file\n* distributed with this work for additional information\n* regarding copyright ownership.  The ASF licenses this file\n* to you under the Apache License, Version 2.0 (the\n* \"License\"); you may not use this file except in compliance\n* with the License.  You may obtain a copy of the License at\n*\n*   http://www.apache.org/licenses/LICENSE-2.0\n*\n* Unless required by applicable law or agreed to in writing,\n* software distributed under the License is distributed on an\n* \"AS IS\" BASIS, WITHOUT WARRANTIES OR CONDITIONS OF ANY\n* KIND, either express or implied.  See the License for the\n* specific language governing permissions and limitations\n* under the License.\n*/\n\n/*\n* Licensed to the Apache Software Foundation (ASF) under one\n* or more contributor license agreements.  See the NOTICE file\n* distributed with this work for additional information\n* regarding copyright ownership.  The ASF licenses this file\n* to you under the Apache License, Version 2.0 (the\n* \"License\"); you may not use this file except in compliance\n* with the License.  You may obtain a copy of the License at\n*\n*   http://www.apache.org/licenses/LICENSE-2.0\n*\n* Unless required by applicable law or agreed to in writing,\n* software distributed under the License is distributed on an\n* \"AS IS\" BASIS, WITHOUT WARRANTIES OR CONDITIONS OF ANY\n* KIND, either express or implied.  See the License for the\n* specific language governing permissions and limitations\n* under the License.\n*/\nfunction _default(ecModel) {\n  var paletteScope = {};\n  ecModel.eachSeriesByType('graph', function (seriesModel) {\n    var categoriesData = seriesModel.getCategoriesData();\n    var data = seriesModel.getData();\n    var categoryNameIdxMap = {};\n    categoriesData.each(function (idx) {\n      var name = categoriesData.getName(idx); // Add prefix to avoid conflict with Object.prototype.\n\n      categoryNameIdxMap['ec-' + name] = idx;\n      var itemModel = categoriesData.getItemModel(idx);\n      var color = itemModel.get('itemStyle.color') || seriesModel.getColorFromPalette(name, paletteScope);\n      categoriesData.setItemVisual(idx, 'color', color);\n    }); // Assign category color to visual\n\n    if (categoriesData.count()) {\n      data.each(function (idx) {\n        var model = data.getItemModel(idx);\n        var category = model.getShallow('category');\n\n        if (category != null) {\n          if (typeof category === 'string') {\n            category = categoryNameIdxMap['ec-' + category];\n          }\n\n          if (!data.getItemVisual(idx, 'color', true)) {\n            data.setItemVisual(idx, 'color', categoriesData.getItemVisual(category, 'color'));\n          }\n        }\n      });\n    }\n  });\n}\n\nmodule.exports = _default;"},"lineCount":null}},"hash":"dae5a7eb51b4833e29bdddf0c6cdd4c2","cacheData":{"env":{}}}