{"id":"F3h9","dependencies":[{"name":"C:\\Users\\user\\Desktop\\铁塔\\tower\\node_modules\\zrender\\package.json","includedInParent":true,"mtime":1577984109926},{"name":"C:\\Users\\user\\Desktop\\铁塔\\tower\\package.json","includedInParent":true,"mtime":1577981361515},{"name":"C:\\Users\\user\\Desktop\\铁塔\\tower\\.babelrc","includedInParent":true,"mtime":1577778028910},{"name":"./Path","loc":{"line":1,"column":19},"parent":"C:\\Users\\user\\Desktop\\铁塔\\tower\\node_modules\\zrender\\lib\\graphic\\CompoundPath.js","resolved":"C:\\Users\\user\\Desktop\\铁塔\\tower\\node_modules\\zrender\\lib\\graphic\\Path.js"}],"generated":{"js":"var t=require(\"./Path\"),h=t.extend({type:\"compound\",shape:{paths:null},_updatePathDirty:function(){for(var t=this.__dirtyPath,h=this.shape.paths,a=0;a<h.length;a++)t=t||h[a].__dirtyPath;this.__dirtyPath=t,this.__dirty=this.__dirty||t},beforeBrush:function(){this._updatePathDirty();for(var t=this.shape.paths||[],h=this.getGlobalScale(),a=0;a<t.length;a++)t[a].path||t[a].createPathProxy(),t[a].path.setScale(h[0],h[1])},buildPath:function(t,h){for(var a=h.paths||[],e=0;e<a.length;e++)a[e].buildPath(t,a[e].shape,!0)},afterBrush:function(){for(var t=this.shape.paths||[],h=0;h<t.length;h++)t[h].__dirtyPath=!1},getBoundingRect:function(){return this._updatePathDirty(),t.prototype.getBoundingRect.call(this)}});module.exports=h;","map":{"mappings":[{"source":"..\\node_modules\\zrender\\lib\\graphic\\CompoundPath.js","original":{"line":1,"column":0},"generated":{"line":1,"column":0}},{"source":"..\\node_modules\\zrender\\lib\\graphic\\CompoundPath.js","original":{"line":1,"column":0},"generated":{"line":1,"column":4}},{"source":"..\\node_modules\\zrender\\lib\\graphic\\CompoundPath.js","original":{"line":1,"column":0},"generated":{"line":1,"column":6}},{"source":"..\\node_modules\\zrender\\lib\\graphic\\CompoundPath.js","original":{"line":1,"column":0},"generated":{"line":1,"column":14}},{"source":"..\\node_modules\\zrender\\lib\\graphic\\CompoundPath.js","original":{"line":4,"column":0},"generated":{"line":1,"column":24}},{"source":"..\\node_modules\\zrender\\lib\\graphic\\CompoundPath.js","original":{"line":4,"column":0},"generated":{"line":1,"column":26}},{"source":"..\\node_modules\\zrender\\lib\\graphic\\CompoundPath.js","original":{"line":4,"column":0},"generated":{"line":1,"column":28}},{"source":"..\\node_modules\\zrender\\lib\\graphic\\CompoundPath.js","original":{"line":4,"column":0},"generated":{"line":1,"column":35}},{"source":"..\\node_modules\\zrender\\lib\\graphic\\CompoundPath.js","original":{"line":5,"column":0},"generated":{"line":1,"column":36}},{"source":"..\\node_modules\\zrender\\lib\\graphic\\CompoundPath.js","original":{"line":5,"column":0},"generated":{"line":1,"column":41}},{"source":"..\\node_modules\\zrender\\lib\\graphic\\CompoundPath.js","original":{"line":6,"column":0},"generated":{"line":1,"column":52}},{"source":"..\\node_modules\\zrender\\lib\\graphic\\CompoundPath.js","original":{"line":6,"column":0},"generated":{"line":1,"column":58}},{"source":"..\\node_modules\\zrender\\lib\\graphic\\CompoundPath.js","original":{"line":7,"column":0},"generated":{"line":1,"column":59}},{"source":"..\\node_modules\\zrender\\lib\\graphic\\CompoundPath.js","original":{"line":7,"column":0},"generated":{"line":1,"column":65}},{"source":"..\\node_modules\\zrender\\lib\\graphic\\CompoundPath.js","original":{"line":9,"column":0},"generated":{"line":1,"column":71}},{"source":"..\\node_modules\\zrender\\lib\\graphic\\CompoundPath.js","original":{"line":9,"column":0},"generated":{"line":1,"column":88}},{"source":"..\\node_modules\\zrender\\lib\\graphic\\CompoundPath.js","original":{"line":13,"column":0},"generated":{"line":1,"column":99}},{"source":"..\\node_modules\\zrender\\lib\\graphic\\CompoundPath.js","original":{"line":10,"column":0},"generated":{"line":1,"column":103}},{"source":"..\\node_modules\\zrender\\lib\\graphic\\CompoundPath.js","original":{"line":10,"column":0},"generated":{"line":1,"column":107}},{"source":"..\\node_modules\\zrender\\lib\\graphic\\CompoundPath.js","original":{"line":10,"column":0},"generated":{"line":1,"column":109}},{"source":"..\\node_modules\\zrender\\lib\\graphic\\CompoundPath.js","original":{"line":10,"column":0},"generated":{"line":1,"column":114}},{"source":"..\\node_modules\\zrender\\lib\\graphic\\CompoundPath.js","original":{"line":11,"column":0},"generated":{"line":1,"column":126}},{"source":"..\\node_modules\\zrender\\lib\\graphic\\CompoundPath.js","original":{"line":11,"column":0},"generated":{"line":1,"column":128}},{"source":"..\\node_modules\\zrender\\lib\\graphic\\CompoundPath.js","original":{"line":11,"column":0},"generated":{"line":1,"column":133}},{"source":"..\\node_modules\\zrender\\lib\\graphic\\CompoundPath.js","original":{"line":11,"column":0},"generated":{"line":1,"column":139}},{"source":"..\\node_modules\\zrender\\lib\\graphic\\CompoundPath.js","original":{"line":13,"column":0},"generated":{"line":1,"column":145}},{"source":"..\\node_modules\\zrender\\lib\\graphic\\CompoundPath.js","original":{"line":13,"column":0},"generated":{"line":1,"column":147}},{"source":"..\\node_modules\\zrender\\lib\\graphic\\CompoundPath.js","original":{"line":13,"column":0},"generated":{"line":1,"column":149}},{"source":"..\\node_modules\\zrender\\lib\\graphic\\CompoundPath.js","original":{"line":13,"column":0},"generated":{"line":1,"column":151}},{"source":"..\\node_modules\\zrender\\lib\\graphic\\CompoundPath.js","original":{"line":13,"column":0},"generated":{"line":1,"column":153}},{"source":"..\\node_modules\\zrender\\lib\\graphic\\CompoundPath.js","original":{"line":13,"column":0},"generated":{"line":1,"column":160}},{"source":"..\\node_modules\\zrender\\lib\\graphic\\CompoundPath.js","original":{"line":15,"column":0},"generated":{"line":1,"column":164}},{"source":"..\\node_modules\\zrender\\lib\\graphic\\CompoundPath.js","original":{"line":15,"column":0},"generated":{"line":1,"column":166}},{"source":"..\\node_modules\\zrender\\lib\\graphic\\CompoundPath.js","original":{"line":15,"column":0},"generated":{"line":1,"column":169}},{"source":"..\\node_modules\\zrender\\lib\\graphic\\CompoundPath.js","original":{"line":15,"column":0},"generated":{"line":1,"column":171}},{"source":"..\\node_modules\\zrender\\lib\\graphic\\CompoundPath.js","original":{"line":15,"column":0},"generated":{"line":1,"column":174}},{"source":"..\\node_modules\\zrender\\lib\\graphic\\CompoundPath.js","original":{"line":18,"column":0},"generated":{"line":1,"column":186}},{"source":"..\\node_modules\\zrender\\lib\\graphic\\CompoundPath.js","original":{"line":18,"column":0},"generated":{"line":1,"column":191}},{"source":"..\\node_modules\\zrender\\lib\\graphic\\CompoundPath.js","original":{"line":18,"column":0},"generated":{"line":1,"column":203}},{"source":"..\\node_modules\\zrender\\lib\\graphic\\CompoundPath.js","original":{"line":19,"column":0},"generated":{"line":1,"column":205}},{"source":"..\\node_modules\\zrender\\lib\\graphic\\CompoundPath.js","original":{"line":19,"column":0},"generated":{"line":1,"column":210}},{"source":"..\\node_modules\\zrender\\lib\\graphic\\CompoundPath.js","original":{"line":19,"column":0},"generated":{"line":1,"column":218}},{"source":"..\\node_modules\\zrender\\lib\\graphic\\CompoundPath.js","original":{"line":19,"column":0},"generated":{"line":1,"column":223}},{"source":"..\\node_modules\\zrender\\lib\\graphic\\CompoundPath.js","original":{"line":19,"column":0},"generated":{"line":1,"column":232}},{"source":"..\\node_modules\\zrender\\lib\\graphic\\CompoundPath.js","original":{"line":21,"column":0},"generated":{"line":1,"column":235}},{"source":"..\\node_modules\\zrender\\lib\\graphic\\CompoundPath.js","original":{"line":21,"column":0},"generated":{"line":1,"column":247}},{"source":"..\\node_modules\\zrender\\lib\\graphic\\CompoundPath.js","original":{"line":22,"column":0},"generated":{"line":1,"column":258}},{"source":"..\\node_modules\\zrender\\lib\\graphic\\CompoundPath.js","original":{"line":22,"column":0},"generated":{"line":1,"column":263}},{"source":"..\\node_modules\\zrender\\lib\\graphic\\CompoundPath.js","original":{"line":27,"column":0},"generated":{"line":1,"column":282}},{"source":"..\\node_modules\\zrender\\lib\\graphic\\CompoundPath.js","original":{"line":24,"column":0},"generated":{"line":1,"column":286}},{"source":"..\\node_modules\\zrender\\lib\\graphic\\CompoundPath.js","original":{"line":24,"column":0},"generated":{"line":1,"column":290}},{"source":"..\\node_modules\\zrender\\lib\\graphic\\CompoundPath.js","original":{"line":24,"column":0},"generated":{"line":1,"column":292}},{"source":"..\\node_modules\\zrender\\lib\\graphic\\CompoundPath.js","original":{"line":24,"column":0},"generated":{"line":1,"column":297}},{"source":"..\\node_modules\\zrender\\lib\\graphic\\CompoundPath.js","original":{"line":24,"column":0},"generated":{"line":1,"column":303}},{"source":"..\\node_modules\\zrender\\lib\\graphic\\CompoundPath.js","original":{"line":24,"column":0},"generated":{"line":1,"column":310}},{"source":"..\\node_modules\\zrender\\lib\\graphic\\CompoundPath.js","original":{"line":25,"column":0},"generated":{"line":1,"column":313}},{"source":"..\\node_modules\\zrender\\lib\\graphic\\CompoundPath.js","original":{"line":25,"column":0},"generated":{"line":1,"column":315}},{"source":"..\\node_modules\\zrender\\lib\\graphic\\CompoundPath.js","original":{"line":25,"column":0},"generated":{"line":1,"column":320}},{"source":"..\\node_modules\\zrender\\lib\\graphic\\CompoundPath.js","original":{"line":27,"column":0},"generated":{"line":1,"column":337}},{"source":"..\\node_modules\\zrender\\lib\\graphic\\CompoundPath.js","original":{"line":27,"column":0},"generated":{"line":1,"column":339}},{"source":"..\\node_modules\\zrender\\lib\\graphic\\CompoundPath.js","original":{"line":27,"column":0},"generated":{"line":1,"column":341}},{"source":"..\\node_modules\\zrender\\lib\\graphic\\CompoundPath.js","original":{"line":27,"column":0},"generated":{"line":1,"column":343}},{"source":"..\\node_modules\\zrender\\lib\\graphic\\CompoundPath.js","original":{"line":27,"column":0},"generated":{"line":1,"column":345}},{"source":"..\\node_modules\\zrender\\lib\\graphic\\CompoundPath.js","original":{"line":27,"column":0},"generated":{"line":1,"column":352}},{"source":"..\\node_modules\\zrender\\lib\\graphic\\CompoundPath.js","original":{"line":28,"column":0},"generated":{"line":1,"column":356}},{"source":"..\\node_modules\\zrender\\lib\\graphic\\CompoundPath.js","original":{"line":28,"column":0},"generated":{"line":1,"column":358}},{"source":"..\\node_modules\\zrender\\lib\\graphic\\CompoundPath.js","original":{"line":28,"column":0},"generated":{"line":1,"column":361}},{"source":"..\\node_modules\\zrender\\lib\\graphic\\CompoundPath.js","original":{"line":29,"column":0},"generated":{"line":1,"column":367}},{"source":"..\\node_modules\\zrender\\lib\\graphic\\CompoundPath.js","original":{"line":29,"column":0},"generated":{"line":1,"column":369}},{"source":"..\\node_modules\\zrender\\lib\\graphic\\CompoundPath.js","original":{"line":29,"column":0},"generated":{"line":1,"column":372}},{"source":"..\\node_modules\\zrender\\lib\\graphic\\CompoundPath.js","original":{"line":32,"column":0},"generated":{"line":1,"column":390}},{"source":"..\\node_modules\\zrender\\lib\\graphic\\CompoundPath.js","original":{"line":32,"column":0},"generated":{"line":1,"column":392}},{"source":"..\\node_modules\\zrender\\lib\\graphic\\CompoundPath.js","original":{"line":32,"column":0},"generated":{"line":1,"column":395}},{"source":"..\\node_modules\\zrender\\lib\\graphic\\CompoundPath.js","original":{"line":32,"column":0},"generated":{"line":1,"column":400}},{"source":"..\\node_modules\\zrender\\lib\\graphic\\CompoundPath.js","original":{"line":32,"column":0},"generated":{"line":1,"column":409}},{"source":"..\\node_modules\\zrender\\lib\\graphic\\CompoundPath.js","original":{"line":32,"column":0},"generated":{"line":1,"column":411}},{"source":"..\\node_modules\\zrender\\lib\\graphic\\CompoundPath.js","original":{"line":32,"column":0},"generated":{"line":1,"column":414}},{"source":"..\\node_modules\\zrender\\lib\\graphic\\CompoundPath.js","original":{"line":32,"column":0},"generated":{"line":1,"column":416}},{"source":"..\\node_modules\\zrender\\lib\\graphic\\CompoundPath.js","original":{"line":35,"column":0},"generated":{"line":1,"column":421}},{"source":"..\\node_modules\\zrender\\lib\\graphic\\CompoundPath.js","original":{"line":35,"column":0},"generated":{"line":1,"column":431}},{"source":"..\\node_modules\\zrender\\lib\\graphic\\CompoundPath.js","original":{"line":35,"column":0},"generated":{"line":1,"column":440}},{"source":"..\\node_modules\\zrender\\lib\\graphic\\CompoundPath.js","original":{"line":35,"column":0},"generated":{"line":1,"column":442}},{"source":"..\\node_modules\\zrender\\lib\\graphic\\CompoundPath.js","original":{"line":38,"column":0},"generated":{"line":1,"column":445}},{"source":"..\\node_modules\\zrender\\lib\\graphic\\CompoundPath.js","original":{"line":36,"column":0},"generated":{"line":1,"column":449}},{"source":"..\\node_modules\\zrender\\lib\\graphic\\CompoundPath.js","original":{"line":36,"column":0},"generated":{"line":1,"column":453}},{"source":"..\\node_modules\\zrender\\lib\\graphic\\CompoundPath.js","original":{"line":36,"column":0},"generated":{"line":1,"column":455}},{"source":"..\\node_modules\\zrender\\lib\\graphic\\CompoundPath.js","original":{"line":36,"column":0},"generated":{"line":1,"column":457}},{"source":"..\\node_modules\\zrender\\lib\\graphic\\CompoundPath.js","original":{"line":36,"column":0},"generated":{"line":1,"column":464}},{"source":"..\\node_modules\\zrender\\lib\\graphic\\CompoundPath.js","original":{"line":38,"column":0},"generated":{"line":1,"column":467}},{"source":"..\\node_modules\\zrender\\lib\\graphic\\CompoundPath.js","original":{"line":38,"column":0},"generated":{"line":1,"column":469}},{"source":"..\\node_modules\\zrender\\lib\\graphic\\CompoundPath.js","original":{"line":38,"column":0},"generated":{"line":1,"column":471}},{"source":"..\\node_modules\\zrender\\lib\\graphic\\CompoundPath.js","original":{"line":38,"column":0},"generated":{"line":1,"column":473}},{"source":"..\\node_modules\\zrender\\lib\\graphic\\CompoundPath.js","original":{"line":38,"column":0},"generated":{"line":1,"column":475}},{"source":"..\\node_modules\\zrender\\lib\\graphic\\CompoundPath.js","original":{"line":38,"column":0},"generated":{"line":1,"column":482}},{"source":"..\\node_modules\\zrender\\lib\\graphic\\CompoundPath.js","original":{"line":39,"column":0},"generated":{"line":1,"column":486}},{"source":"..\\node_modules\\zrender\\lib\\graphic\\CompoundPath.js","original":{"line":39,"column":0},"generated":{"line":1,"column":488}},{"source":"..\\node_modules\\zrender\\lib\\graphic\\CompoundPath.js","original":{"line":39,"column":0},"generated":{"line":1,"column":491}},{"source":"..\\node_modules\\zrender\\lib\\graphic\\CompoundPath.js","original":{"line":39,"column":0},"generated":{"line":1,"column":501}},{"source":"..\\node_modules\\zrender\\lib\\graphic\\CompoundPath.js","original":{"line":39,"column":0},"generated":{"line":1,"column":503}},{"source":"..\\node_modules\\zrender\\lib\\graphic\\CompoundPath.js","original":{"line":39,"column":0},"generated":{"line":1,"column":505}},{"source":"..\\node_modules\\zrender\\lib\\graphic\\CompoundPath.js","original":{"line":39,"column":0},"generated":{"line":1,"column":508}},{"source":"..\\node_modules\\zrender\\lib\\graphic\\CompoundPath.js","original":{"line":39,"column":0},"generated":{"line":1,"column":515}},{"source":"..\\node_modules\\zrender\\lib\\graphic\\CompoundPath.js","original":{"line":42,"column":0},"generated":{"line":1,"column":519}},{"source":"..\\node_modules\\zrender\\lib\\graphic\\CompoundPath.js","original":{"line":42,"column":0},"generated":{"line":1,"column":530}},{"source":"..\\node_modules\\zrender\\lib\\graphic\\CompoundPath.js","original":{"line":45,"column":0},"generated":{"line":1,"column":541}},{"source":"..\\node_modules\\zrender\\lib\\graphic\\CompoundPath.js","original":{"line":43,"column":0},"generated":{"line":1,"column":545}},{"source":"..\\node_modules\\zrender\\lib\\graphic\\CompoundPath.js","original":{"line":43,"column":0},"generated":{"line":1,"column":549}},{"source":"..\\node_modules\\zrender\\lib\\graphic\\CompoundPath.js","original":{"line":43,"column":0},"generated":{"line":1,"column":551}},{"source":"..\\node_modules\\zrender\\lib\\graphic\\CompoundPath.js","original":{"line":43,"column":0},"generated":{"line":1,"column":556}},{"source":"..\\node_modules\\zrender\\lib\\graphic\\CompoundPath.js","original":{"line":43,"column":0},"generated":{"line":1,"column":562}},{"source":"..\\node_modules\\zrender\\lib\\graphic\\CompoundPath.js","original":{"line":43,"column":0},"generated":{"line":1,"column":569}},{"source":"..\\node_modules\\zrender\\lib\\graphic\\CompoundPath.js","original":{"line":45,"column":0},"generated":{"line":1,"column":572}},{"source":"..\\node_modules\\zrender\\lib\\graphic\\CompoundPath.js","original":{"line":45,"column":0},"generated":{"line":1,"column":574}},{"source":"..\\node_modules\\zrender\\lib\\graphic\\CompoundPath.js","original":{"line":45,"column":0},"generated":{"line":1,"column":576}},{"source":"..\\node_modules\\zrender\\lib\\graphic\\CompoundPath.js","original":{"line":45,"column":0},"generated":{"line":1,"column":578}},{"source":"..\\node_modules\\zrender\\lib\\graphic\\CompoundPath.js","original":{"line":45,"column":0},"generated":{"line":1,"column":580}},{"source":"..\\node_modules\\zrender\\lib\\graphic\\CompoundPath.js","original":{"line":45,"column":0},"generated":{"line":1,"column":587}},{"source":"..\\node_modules\\zrender\\lib\\graphic\\CompoundPath.js","original":{"line":46,"column":0},"generated":{"line":1,"column":591}},{"source":"..\\node_modules\\zrender\\lib\\graphic\\CompoundPath.js","original":{"line":46,"column":0},"generated":{"line":1,"column":593}},{"source":"..\\node_modules\\zrender\\lib\\graphic\\CompoundPath.js","original":{"line":46,"column":0},"generated":{"line":1,"column":596}},{"source":"..\\node_modules\\zrender\\lib\\graphic\\CompoundPath.js","original":{"line":46,"column":0},"generated":{"line":1,"column":609}},{"source":"..\\node_modules\\zrender\\lib\\graphic\\CompoundPath.js","original":{"line":49,"column":0},"generated":{"line":1,"column":612}},{"source":"..\\node_modules\\zrender\\lib\\graphic\\CompoundPath.js","original":{"line":49,"column":0},"generated":{"line":1,"column":628}},{"source":"..\\node_modules\\zrender\\lib\\graphic\\CompoundPath.js","original":{"line":52,"column":0},"generated":{"line":1,"column":639}},{"source":"..\\node_modules\\zrender\\lib\\graphic\\CompoundPath.js","original":{"line":50,"column":0},"generated":{"line":1,"column":646}},{"source":"..\\node_modules\\zrender\\lib\\graphic\\CompoundPath.js","original":{"line":50,"column":0},"generated":{"line":1,"column":651}},{"source":"..\\node_modules\\zrender\\lib\\graphic\\CompoundPath.js","original":{"line":52,"column":0},"generated":{"line":1,"column":670}},{"source":"..\\node_modules\\zrender\\lib\\graphic\\CompoundPath.js","original":{"line":52,"column":0},"generated":{"line":1,"column":672}},{"source":"..\\node_modules\\zrender\\lib\\graphic\\CompoundPath.js","original":{"line":52,"column":0},"generated":{"line":1,"column":682}},{"source":"..\\node_modules\\zrender\\lib\\graphic\\CompoundPath.js","original":{"line":52,"column":0},"generated":{"line":1,"column":698}},{"source":"..\\node_modules\\zrender\\lib\\graphic\\CompoundPath.js","original":{"line":52,"column":0},"generated":{"line":1,"column":703}},{"source":"..\\node_modules\\zrender\\lib\\graphic\\CompoundPath.js","original":{"line":56,"column":0},"generated":{"line":1,"column":712}},{"source":"..\\node_modules\\zrender\\lib\\graphic\\CompoundPath.js","original":{"line":56,"column":0},"generated":{"line":1,"column":719}},{"source":"..\\node_modules\\zrender\\lib\\graphic\\CompoundPath.js","original":{"line":56,"column":0},"generated":{"line":1,"column":727}}],"sources":{"..\\node_modules\\zrender\\lib\\graphic\\CompoundPath.js":"var Path = require(\"./Path\");\n\n// CompoundPath to improve performance\nvar _default = Path.extend({\n  type: 'compound',\n  shape: {\n    paths: null\n  },\n  _updatePathDirty: function () {\n    var dirtyPath = this.__dirtyPath;\n    var paths = this.shape.paths;\n\n    for (var i = 0; i < paths.length; i++) {\n      // Mark as dirty if any subpath is dirty\n      dirtyPath = dirtyPath || paths[i].__dirtyPath;\n    }\n\n    this.__dirtyPath = dirtyPath;\n    this.__dirty = this.__dirty || dirtyPath;\n  },\n  beforeBrush: function () {\n    this._updatePathDirty();\n\n    var paths = this.shape.paths || [];\n    var scale = this.getGlobalScale(); // Update path scale\n\n    for (var i = 0; i < paths.length; i++) {\n      if (!paths[i].path) {\n        paths[i].createPathProxy();\n      }\n\n      paths[i].path.setScale(scale[0], scale[1]);\n    }\n  },\n  buildPath: function (ctx, shape) {\n    var paths = shape.paths || [];\n\n    for (var i = 0; i < paths.length; i++) {\n      paths[i].buildPath(ctx, paths[i].shape, true);\n    }\n  },\n  afterBrush: function () {\n    var paths = this.shape.paths || [];\n\n    for (var i = 0; i < paths.length; i++) {\n      paths[i].__dirtyPath = false;\n    }\n  },\n  getBoundingRect: function () {\n    this._updatePathDirty();\n\n    return Path.prototype.getBoundingRect.call(this);\n  }\n});\n\nmodule.exports = _default;"},"lineCount":null}},"hash":"be36b263ca7b5a7634272461fac8403b","cacheData":{"env":{}}}